url_checker/__init__.py
url_checker/engine.py
url_checker/test_module.py
url_checker-1.5.0.dist-info/LICENSE
url_checker-1.5.0.dist-info/WHEEL
url_checker-1.5.0.dist-info/METADATA
url_checker-1.5.0.dist-info/RECORD
