Metadata-Version: 2.1
Name: url_checker
Version: 1.5.0
Summary: format_url:
Home-page: https://gitlab.com/cw-andrews/url-checker
License: UNKNOWN
Author: cw-andrews
Author-email: cwandrews.oh@gmail.com
Requires-Python: >=3.6
Classifier: License :: OSI Approved :: MIT License
Requires-Dist: attrs==17.4.0
Requires-Dist: certifi==2018.4.16
Requires-Dist: chardet==3.0.4
Requires-Dist: colorama==0.3.9
Requires-Dist: idna==2.6
Requires-Dist: Logbook==1.3.3
Requires-Dist: more-itertools==4.1.0
Requires-Dist: pluggy==0.6.0
Requires-Dist: py==1.5.3
Requires-Dist: pytest==3.5.1
Requires-Dist: requests==2.18.4
Requires-Dist: requests-mock==1.4.0
Requires-Dist: six==1.11.0
Requires-Dist: urllib3==1.22
Requires-Dist: wincertstore==0.2
